kassalappy/__init__.py
kassalappy/cli.py
kassalappy/client.py
kassalappy/const.py
kassalappy/exceptions.py
kassalappy/models.py
kassalappy/py.typed
kassalappy/version.py
kassalappy-1.2.0.dist-info/METADATA
kassalappy-1.2.0.dist-info/WHEEL
kassalappy-1.2.0.dist-info/entry_points.txt
kassalappy-1.2.0.dist-info/RECORD
