Metadata-Version: 2.1
Name: kassalappy
Version: 1.2.0
Summary: Python client for the Kassal.app API
Home-page: https://github.com/bendikrb/kassalappy
License: MIT
Author: Bendik R. Brenne
Author-email: bendik@konstant.no
Requires-Python: >=3.10,<3.13
Classifier: License :: OSI Approved :: MIT License
Classifier: Programming Language :: Python :: 3
Classifier: Programming Language :: Python :: 3.10
Classifier: Programming Language :: Python :: 3.11
Classifier: Programming Language :: Python :: 3.12
Requires-Dist: aiohttp (>=3.11,<4.0)
Requires-Dist: async-timeout (>=4.0.3,<5.0.0)
Requires-Dist: asyncclick (>=8.1.7.2,<9.0.0.0)
Requires-Dist: mashumaro[orjson] (>=3.13.1,<4.0.0)
Requires-Dist: tabulate (>=0.9.0,<0.10.0)
Project-URL: Repository, https://github.com/bendikrb/kassalappy
